aur_deploy/__init__.py
aur_deploy/__main__.py
aur_deploy/aur_deploy.py
aur_deploy-0.9.3.dist-info/LICENSE
aur_deploy-0.9.3.dist-info/METADATA
aur_deploy-0.9.3.dist-info/WHEEL
aur_deploy-0.9.3.dist-info/entry_points.txt
aur_deploy-0.9.3.dist-info/top_level.txt
aur_deploy-0.9.3.dist-info/RECORD
