Metadata-Version: 2.1
Name: aur-deploy
Version: 0.9.3
Summary: Automate updating pkgbuild and deploying to AUR
Home-page: https://github.com/codeswhite/aur-deploy
Author: Max G
Author-email: max3227@gmail.com
License: UNKNOWN
Keywords: aur,archlinux,build,deploy,publish
Platform: UNKNOWN
Classifier: Programming Language :: Python :: 3
Classifier: License :: OSI Approved :: MIT License
Classifier: Operating System :: OS Independent
Classifier: Intended Audience :: Developers
Classifier: Topic :: Software Development :: Build Tools
Requires-Python: >=3.6
License-File: LICENSE
Requires-Dist: interutils
Requires-Dist: requests
Requires-Dist: bs4
